Workbook

Sheet Scout Accounts
A1: CUB SCOUT PACK FINANCIAL TRACKER - SCOUT ACCOUNTS SUMMARY
A3: This sheet shows current balances. Use the "Transaction Ledger" sheet to record all deposits and withdrawals.
A5: INDIVIDUAL SCOUT ACCOUNT BALANCES
A6: Scout Name | B6: Beginning Balance | C6: Total Deposits | D6: Total Withdrawals | E6: Current Balance | F6: Pack Dues Paid? | G6: Payment Method | H6: Notes
A7: Scout 1 | B7: 0 | C7: =SUMIFS(Ledger!$E:$E,Ledger!$B:$B,A7,Ledger!$D:$D,"Deposit")+SUMIFS(Ledger!$E:$E,Ledger!$B:$B,A7,Ledger!$D:$D,"Reimbursement") -> 200 | D7: =SUMIFS(Ledger!$E:$E,Ledger!$B:$B,A7,Ledger!$D:$D,"Withdrawal") -> 0 | E7: =B7+C7-D7 -> 200 | F7: =IF(COUNTIFS(Ledger!$B:$B,A7,Ledger!$C:$C,"Pack Dues")>0,"✓ Paid","") | G7: =IF(COUNTIFS(Ledger!$B:$B,A7,Ledger!$C:$C,"Pack Dues",Ledger!$D:$D,"Withdrawal")>0,"Scout Account",IF(COUNTIFS(Ledger!$B:$B,A7,Ledger!$C:$C,"Pack Dues")>0,"Family Cash",""))
A8: Scout 2 | B8: 0 | C8: =SUMIFS(Ledger!$E:$E,Ledger!$B:$B,A8,Ledger!$D:$D,"Deposit")+SUMIFS(Ledger!$E:$E,Ledger!$B:$B,A8,Ledger!$D:$D,"Reimbursement") -> 250 | D8: =SUMIFS(Ledger!$E:$E,Ledger!$B:$B,A8,Ledger!$D:$D,"Withdrawal") -> 0 | E8: =B8+C8-D8 -> 250 | F8: =IF(COUNTIFS(Ledger!$B:$B,A8,Ledger!$C:$C,"Pack Dues")>0,"✓ Paid","") -> ✓ Paid | G8: =IF(COUNTIFS(Ledger!$B:$B,A8,Ledger!$C:$C,"Pack Dues",Ledger!$D:$D,"Withdrawal")>0,"Scout Account",IF(COUNTIFS(Ledger!$B:$B,A8,Ledger!$C:$C,"Pack Dues")>0,"Family Cash","")) -> Family Cash
A9: Scout 3 | B9: 0 | C9: =SUMIFS(Ledger!$E:$E,Ledger!$B:$B,A9,Ledger!$D:$D,"Deposit")+SUMIFS(Ledger!$E:$E,Ledger!$B:$B,A9,Ledger!$D:$D,"Reimbursement") -> 0 | D9: =SUMIFS(Ledger!$E:$E,Ledger!$B:$B,A9,Ledger!$D:$D,"Withdrawal") -> 300 | E9: =B9+C9-D9 -> -300 | F9: =IF(COUNTIFS(Ledger!$B:$B,A9,Ledger!$C:$C,"Pack Dues")>0,"✓ Paid","") | G9: =IF(COUNTIFS(Ledger!$B:$B,A9,Ledger!$C:$C,"Pack Dues",Ledger!$D:$D,"Withdrawal")>0,"Scout Account",IF(COUNTIFS(Ledger!$B:$B,A9,Ledger!$C:$C,"Pack Dues")>0,"Family Cash",""))
A10: Scout 4 | B10: 0 | C10: =SUMIFS(Ledger!$E:$E,Ledger!$B:$B,A10,Ledger!$D:$D,"Deposit")+SUMIFS(Ledger!$E:$E,Ledger!$B:$B,A10,Ledger!$D:$D,"Reimbursement") -> 75 | D10: =SUMIFS(Ledger!$E:$E,Ledger!$B:$B,A10,Ledger!$D:$D,"Withdrawal") -> 0 | E10: =B10+C10-D10 -> 75 | F10: =IF(COUNTIFS(Ledger!$B:$B,A10,Ledger!$C:$C,"Pack Dues")>0,"✓ Paid","") | G10: =IF(COUNTIFS(Ledger!$B:$B,A10,Ledger!$C:$C,"Pack Dues",Ledger!$D:$D,"Withdrawal")>0,"Scout Account",IF(COUNTIFS(Ledger!$B:$B,A10,Ledger!$C:$C,"Pack Dues")>0,"Family Cash",""))
A11: Scout 5 | B11: 0 | C11: =SUMIFS(Ledger!$E:$E,Ledger!$B:$B,A11,Ledger!$D:$D,"Deposit")+SUMIFS(Ledger!$E:$E,Ledger!$B:$B,A11,Ledger!$D:$D,"Reimbursement") -> 0 | D11: =SUMIFS(Ledger!$E:$E,Ledger!$B:$B,A11,Ledger!$D:$D,"Withdrawal") -> 0 | E11: =B11+C11-D11 -> 0 | F11: =IF(COUNTIFS(Ledger!$B:$B,A11,Ledger!$C:$C,"Pack Dues")>0,"✓ Paid","") | G11: =IF(COUNTIFS(Ledger!$B:$B,A11,Ledger!$C:$C,"Pack Dues",Ledger!$D:$D,"Withdrawal")>0,"Scout Account",IF(COUNTIFS(Ledger!$B:$B,A11,Ledger!$C:$C,"Pack Dues")>0,"Family Cash",""))
A12: Scout 6 | B12: 0 | C12: =SUMIFS(Ledger!$E:$E,Ledger!$B:$B,A12,Ledger!$D:$D,"Deposit")+SUMIFS(Ledger!$E:$E,Ledger!$B:$B,A12,Ledger!$D:$D,"Reimbursement") -> 0 | D12: =SUMIFS(Ledger!$E:$E,Ledger!$B:$B,A12,Ledger!$D:$D,"Withdrawal") -> 0 | E12: =B12+C12-D12 -> 0 | F12: =IF(COUNTIFS(Ledger!$B:$B,A12,Ledger!$C:$C,"Pack Dues")>0,"✓ Paid","") | G12: =IF(COUNTIFS(Ledger!$B:$B,A12,Ledger!$C:$C,"Pack Dues",Ledger!$D:$D,"Withdrawal")>0,"Scout Account",IF(COUNTIFS(Ledger!$B:$B,A12,Ledger!$C:$C,"Pack Dues")>0,"Family Cash",""))
A13: Scout 7 | B13: 0 | C13: =SUMIFS(Ledger!$E:$E,Ledger!$B:$B,A13,Ledger!$D:$D,"Deposit")+SUMIFS(Ledger!$E:$E,Ledger!$B:$B,A13,Ledger!$D:$D,"Reimbursement") -> 0 | D13: =SUMIFS(Ledger!$E:$E,Ledger!$B:$B,A13,Ledger!$D:$D,"Withdrawal") -> 0 | E13: =B13+C13-D13 -> 0 | F13: =IF(COUNTIFS(Ledger!$B:$B,A13,Ledger!$C:$C,"Pack Dues")>0,"✓ Paid","") | G13: =IF(COUNTIFS(Ledger!$B:$B,A13,Ledger!$C:$C,"Pack Dues",Ledger!$D:$D,"Withdrawal")>0,"Scout Account",IF(COUNTIFS(Ledger!$B:$B,A13,Ledger!$C:$C,"Pack Dues")>0,"Family Cash",""))
A14: Scout 8 | B14: 0 | C14: =SUMIFS(Ledger!$E:$E,Ledger!$B:$B,A14,Ledger!$D:$D,"Deposit")+SUMIFS(Ledger!$E:$E,Ledger!$B:$B,A14,Ledger!$D:$D,"Reimbursement") -> 0 | D14: =SUMIFS(Ledger!$E:$E,Ledger!$B:$B,A14,Ledger!$D:$D,"Withdrawal") -> 0 | E14: =B14+C14-D14 -> 0 | F14: =IF(COUNTIFS(Ledger!$B:$B,A14,Ledger!$C:$C,"Pack Dues")>0,"✓ Paid","") | G14: =IF(COUNTIFS(Ledger!$B:$B,A14,Ledger!$C:$C,"Pack Dues",Ledger!$D:$D,"Withdrawal")>0,"Scout Account",IF(COUNTIFS(Ledger!$B:$B,A14,Ledger!$C:$C,"Pack Dues")>0,"Family Cash",""))
A15: Scout 9 | B15: 0 | C15: =SUMIFS(Ledger!$E:$E,Ledger!$B:$B,A15,Ledger!$D:$D,"Deposit")+SUMIFS(Ledger!$E:$E,Ledger!$B:$B,A15,Ledger!$D:$D,"Reimbursement") -> 0 | D15: =SUMIFS(Ledger!$E:$E,Ledger!$B:$B,A15,Ledger!$D:$D,"Withdrawal") -> 0 | E15: =B15+C15-D15 -> 0 | F15: =IF(COUNTIFS(Ledger!$B:$B,A15,Ledger!$C:$C,"Pack Dues")>0,"✓ Paid","") | G15: =IF(COUNTIFS(Ledger!$B:$B,A15,Ledger!$C:$C,"Pack Dues",Ledger!$D:$D,"Withdrawal")>0,"Scout Account",IF(COUNTIFS(Ledger!$B:$B,A15,Ledger!$C:$C,"Pack Dues")>0,"Family Cash",""))
A16: Scout 10 | B16: 0 | C16: =SUMIFS(Ledger!$E:$E,Ledger!$B:$B,A16,Ledger!$D:$D,"Deposit")+SUMIFS(Ledger!$E:$E,Ledger!$B:$B,A16,Ledger!$D:$D,"Reimbursement") -> 0 | D16: =SUMIFS(Ledger!$E:$E,Ledger!$B:$B,A16,Ledger!$D:$D,"Withdrawal") -> 0 | E16: =B16+C16-D16 -> 0 | F16: =IF(COUNTIFS(Ledger!$B:$B,A16,Ledger!$C:$C,"Pack Dues")>0,"✓ Paid","") | G16: =IF(COUNTIFS(Ledger!$B:$B,A16,Ledger!$C:$C,"Pack Dues",Ledger!$D:$D,"Withdrawal")>0,"Scout Account",IF(COUNTIFS(Ledger!$B:$B,A16,Ledger!$C:$C,"Pack Dues")>0,"Family Cash",""))
A17: Scout 11 | B17: 0 | C17: =SUMIFS(Ledger!$E:$E,Ledger!$B:$B,A17,Ledger!$D:$D,"Deposit")+SUMIFS(Ledger!$E:$E,Ledger!$B:$B,A17,Ledger!$D:$D,"Reimbursement") -> 0 | D17: =SUMIFS(Ledger!$E:$E,Ledger!$B:$B,A17,Ledger!$D:$D,"Withdrawal") -> 0 | E17: =B17+C17-D17 -> 0 | F17: =IF(COUNTIFS(Ledger!$B:$B,A17,Ledger!$C:$C,"Pack Dues")>0,"✓ Paid","") | G17: =IF(COUNTIFS(Ledger!$B:$B,A17,Ledger!$C:$C,"Pack Dues",Ledger!$D:$D,"Withdrawal")>0,"Scout Account",IF(COUNTIFS(Ledger!$B:$B,A17,Ledger!$C:$C,"Pack Dues")>0,"Family Cash",""))
A18: Scout 12 | B18: 0 | C18: =SUMIFS(Ledger!$E:$E,Ledger!$B:$B,A18,Ledger!$D:$D,"Deposit")+SUMIFS(Ledger!$E:$E,Ledger!$B:$B,A18,Ledger!$D:$D,"Reimbursement") -> 0 | D18: =SUMIFS(Ledger!$E:$E,Ledger!$B:$B,A18,Ledger!$D:$D,"Withdrawal") -> 0 | E18: =B18+C18-D18 -> 0 | F18: =IF(COUNTIFS(Ledger!$B:$B,A18,Ledger!$C:$C,"Pack Dues")>0,"✓ Paid","") | G18: =IF(COUNTIFS(Ledger!$B:$B,A18,Ledger!$C:$C,"Pack Dues",Ledger!$D:$D,"Withdrawal")>0,"Scout Account",IF(COUNTIFS(Ledger!$B:$B,A18,Ledger!$C:$C,"Pack Dues")>0,"Family Cash",""))
... A46: Scout 40 | B46: 0 | C46: =SUMIFS(Ledger!$E:$E,Ledger!$B:$B,A46,Ledger!$D:$D,"Deposit")+SUMIFS(Ledger!$E:$E,Ledger!$B:$B,A46,Ledger!$D:$D,"Reimbursement") -> 0 | D46: =SUMIFS(Ledger!$E:$E,Ledger!$B:$B,A46,Ledger!$D:$D,"Withdrawal") -> 0 | E46: =B46+C46-D46 -> 0 | F46: =IF(COUNTIFS(Ledger!$B:$B,A46,Ledger!$C:$C,"Pack Dues")>0,"✓ Paid","") | G46: =IF(COUNTIFS(Ledger!$B:$B,A46,Ledger!$C:$C,"Pack Dues",Ledger!$D:$D,"Withdrawal")>0,"Scout Account",IF(COUNTIFS(Ledger!$B:$B,A46,Ledger!$C:$C,"Pack Dues")>0,"Family Cash",""))
A48: TOTALS | B48: =SUM(B7:B46) -> 0 | C48: =SUM(C7:C46) -> 525 | D48: =SUM(D7:D46) -> 300 | E48: =SUM(E7:E46) -> 225
A50: PAYMENT SUMMARY
A51: Scouts Paid via Account | B51: =COUNTIF(G7:G46,"Scout Account") -> 0
A52: Scouts Paid via Cash | B52: =COUNTIF(G7:G46,"Family Cash") -> 1
A53: Still Need to Pay | B53: =40-B51-B52 -> 39

Sheet Ledger
A1: TRANSACTION LEDGER - ALL SCOUT ACCOUNT ACTIVITY
A3: Record ALL transactions here. Scout account balances update automatically.
A5: Date | B5: Scout Name | C5: Description | D5: Type | E5: Amount | F5: Pack Gets (25%) | G5: Notes
A6: 1/1/2025 | B6: Scout 1 | C6: Popcorn Sales | D6: Deposit | E6: 200 | F6: =IF(OR(D6="Deposit",D6="Reimbursement"),E6*0.25,0) -> 50 | G6: Fall fundraiser
A7: 1/1/2025 | B7: Scout 2 | C7: Pack Dues | D7: Pack Dues Paid | E7: 100 | G7: Family paid cash up front
A8: 1/15/2025 | B8: Scout 2 | C8: Wreath Sales | D8: Deposit | E8: 150 | F8: =IF(OR(D7="Deposit",D7="Reimbursement"),E7*0.25,0) -> 0 | G8: Winter fundraiser
A9: 1/20/2025 | B9: Scout 2 | C9: Pack Dues Reimbursement | D9: Reimbursement | E9: 100 | F9: =IF(OR(D8="Deposit",D8="Reimbursement"),E8*0.25,0) -> 37.5 | G9: Reimburse family for cash payment
A10: 2/1/2025 | B10: Scout 3 | C10: Camp Fee | D10: Withdrawal | E10: 300 | G10: Family Campout registration
A11: 2/10/2025 | B11: Scout 4 | C11: Car Wash | D11: Deposit | E11: 75 | F11: =IF(OR(D10="Deposit",D10="Reimbursement"),E10*0.25,0) -> 0 | G11: Den fundraiser
G12: Add new transactions below...
F13: =IF(OR(D13="Deposit",D13="Reimbursement"),E13*0.25,0) -> 0
F14: =IF(OR(D14="Deposit",D14="Reimbursement"),E14*0.25,0) -> 0
F15: =IF(OR(D15="Deposit",D15="Reimbursement"),E15*0.25,0) -> 0
F16: =IF(OR(D16="Deposit",D16="Reimbursement"),E16*0.25,0) -> 0
F17: =IF(OR(D17="Deposit",D17="Reimbursement"),E17*0.25,0) -> 0
F18: =IF(OR(D18="Deposit",D18="Reimbursement"),E18*0.25,0) -> 0
F19: =IF(OR(D19="Deposit",D19="Reimbursement"),E19*0.25,0) -> 0
F20: =IF(OR(D20="Deposit",D20="Reimbursement"),E20*0.25,0) -> 0
F21: =IF(OR(D21="Deposit",D21="Reimbursement"),E21*0.25,0) -> 0
F22: =IF(OR(D22="Deposit",D22="Reimbursement"),E22*0.25,0) -> 0
F23: =IF(OR(D23="Deposit",D23="Reimbursement"),E23*0.25,0) -> 0
F24: =IF(OR(D24="Deposit",D24="Reimbursement"),E24*0.25,0) -> 0
... F212: =IF(OR(D212="Deposit",D212="Reimbursement"),E212*0.25,0) -> 0
A215: LEDGER SUMMARY
A216: Total Fundraising Deposits | B216: =SUMIF(D:D,"Deposit",E:E) -> 425
A217: Total Withdrawals | B217: =SUMIF(D:D,"Withdrawal",E:E) -> 300
A218: Total Reimbursements to Scouts | B218: =SUMIF(D:D,"Reimbursement",E:E) -> 100
A219: Pack Share from Fundraising (25%) | B219: =SUM(F:F) -> 87.5

Sheet Pack Finances
A1: PACK GENERAL FUND LEDGER
A3: Track all pack-level income and expenses here
A5: PACK FUND SUMMARY
A7: Pack Dues from Scout Accounts | B7: =COUNTIFS(Ledger!$C:$C,"Pack Dues",Ledger!$D:$D,"Withdrawal")*100 -> 0 | C7: Scouts who paid from their account
A8: Pack Dues from Family Cash | B8: =COUNTIF(Ledger!$D:$D,"Pack Dues Paid")*100 -> 100 | C8: Families who paid cash up front
A9: Total Pack Dues Collected | B9: =B7+B8 -> 100
A11: Fundraising Share (25%) | B11: =Ledger!$B$219 -> 87.5
A12: Other Pack Income | B12: =SUMIF(C:C,"Income",D:D) -> 500
A14: TOTAL PACK REVENUE | B14: =B9+B11+B12 -> 687.5
A16: Total Pack Expenses | B16: =SUMIF(C:C,"Expense",D:D) -> 1800
A17: Reimbursements Paid to Scouts | B17: =Ledger!$B$218 -> 100
A19: CURRENT PACK BALANCE | B19: =B14-B16-B17 -> -1212.5
A22: PACK TRANSACTION LEDGER
A23: Date | B23: Description | C23: Type | D23: Amount | E23: Category | F23: Notes
A24: 1/1/2025 | B24: Adult Leader Registrations | C24: Expense | D24: 875 | E24: Registration | F24: 7 leaders @ $125
A25: 1/15/2025 | B25: Awards & Patches Purchase | C25: Expense | D25: 245 | E25: Awards | F25: Belt loops and patches
A26: 2/1/2025 | B26: Blue & Gold Banquet Supplies | C26: Expense | D26: 380 | E26: Events | F26: Decorations and awards
A27: 2/1/2025 | B27: Direct Donation from Local Business | C27: Income | D27: 500 | E27: Donation | F27: Thanks to XYZ Corp
A28: 2/15/2025 | B28: Charter Renewal Fee | C28: Expense | D28: 300 | E28: Charter | F28: Annual recharter
F29: Add new transactions below...

Sheet Instructions
A1: HOW TO USE THE LEDGER SYSTEM
A4: OVERVIEW:
A5: This workbook tracks both individual scout accounts and pack finances with flexible payment options.
A6: Scouts can pay pack dues from their account OR families can pay cash up front and be reimbursed later.
A8: ━━━━━━━━━━━━━━━━━━━━━━━━━━━━━━━━━━━━━━━━━━━━━━━━━━━━━━━━━━━━━━━━━━
A9: TRANSACTION TYPES (Use in Ledger sheet, Column D):
A10: ━━━━━━━━━━━━━━━━━━━━━━━━━━━━━━━━━━━━━━━━━━━━━━━━━━━━━━━━━━━━━━━━━━
A12: 1. "Deposit" - Money INTO scout account from fundraising
A13: → Scout gets 75%, Pack gets 25%
A14: → Use for: Popcorn sales, wreath sales, car wash, any fundraiser
A16: 2. "Withdrawal" - Money OUT of scout account
A17: → Deducts from scout balance
... A184: - But then you lose the 25% pack share from that transaction
